{
	"NeutralStates": [
		{
			"Name": "CmnStand",
			"Position": "Standing",
			"Input": "_5",
			"Button": 0,
			"Priority": 0,
			"CancelType": "OnlyNeutral",
			"CounterType": "None",
			"HitOrBlockCancels": [],
			"HitCancels": [],
			"WhiffCancels": [],
			"Looping": true,
			"LoopPos": 0,
			"NextState": "",
			"LandToState": false,
			"LandState": "",
			"StateCanTurn": true,
			"TurnState": "CmnStandTurn"
		},
		{
			"Name": "CmnFWalk",
			"Position": "Standing",
			"Input": "_6",
			"Button": 0,
			"Priority": 1,
			"CancelType": "OnlyNeutral",
			"CounterType": "None",
			"HitOrBlockCancels": [],
			"HitCancels": [],
			"WhiffCancels": [],
			"Looping": true,
			"LoopPos": 2,
			"NextState": "",
			"LandToState": false,
			"LandState": "",
			"StateCanTurn": false,
			"TurnState": ""
		},{
			"Name": "CmnFDash",
			"Position": "Standing",
			"Input": "_66",
			"Button": 0,
			"Priority": 2,
			"CancelType": "OnlyNeutral",
			"CounterType": "None",
			"HitOrBlockCancels": [],
			"HitCancels": [],
			"WhiffCancels": [],
			"Looping": true,
			"LoopPos": 1,
			"NextState": "",
			"LandToState": false,
			"LandState": "",
			"StateCanTurn": false,
			"TurnState": ""
		},
		{
			"Name": "CmnBWalk",
			"Position": "Standing",
			"Input": "_4",
			"Button": 0,
			"Priority": 1,
			"CancelType": "OnlyNeutral",
			"CounterType": "None",
			"HitOrBlockCancels": [],
			"HitCancels": [],
			"WhiffCancels": [],
			"Looping": true,
			"LoopPos": 2,
			"NextState": "",
			"LandToState": false,
			"LandState": "",
			"StateCanTurn": false,
			"TurnState": ""
		},
		{
			"Name": "CmnStandTurn",
			"Position": "Standing",
			"Input": "_5",
			"Button": 0,
			"Priority": 0,
			"CancelType": "OnlyWhenSpecified",
			"CounterType": "None",
			"HitOrBlockCancels": [],
			"HitCancels": [],
			"WhiffCancels": [],
			"Looping": false,
			"LoopPos": 0,
			"NextState": "CmnStand",
			"LandToState": false,
			"LandState": "",
			"StateCanTurn": false,
			"TurnState": ""
		},
		{
			"Name": "CmnStandToCrouch",
			"Position": "Standing",
			"Input": "_2",
			"Button": 0,
			"Priority": 0,
			"CancelType": "OnlyNeutral",
			"CounterType": "None",
			"HitOrBlockCancels": [],
			"HitCancels": [],
			"WhiffCancels": [],
			"Looping": false,
			"LoopPos": 0,
			"NextState": "CmnCrouch",
			"LandToState": false,
			"LandState": "",
			"StateCanTurn": false,
			"TurnState": ""
		},
		{
			"Name": "CmnCrouch",
			"Position": "Crouching",
			"Input": "_2",
			"Button": 0,
			"Priority": 0,
			"CancelType": "OnlyNeutral",
			"CounterType": "None",
			"HitOrBlockCancels": [],
			"HitCancels": [],
			"WhiffCancels": [],
			"Looping": true,
			"LoopPos": 0,
			"NextState": "",
			"LandToState": false,
			"LandState": "",
			"StateCanTurn": false,
			"TurnState": ""
		},
		{
			"Name": "CmnCrouchToStand",
			"Position": "Crouching",
			"Input": "_5",
			"Button": 0,
			"Priority": 1,
			"CancelType": "OnlyNeutral",
			"CounterType": "None",
			"HitOrBlockCancels": [],
			"HitCancels": [],
			"WhiffCancels": [],
			"Looping": false,
			"LoopPos": 0,
			"NextState": "CmnStand",
			"LandToState": false,
			"LandState": "",
			"StateCanTurn": false,
			"TurnState": ""
		}
	],
	"NormalStates": [
		{
			"Name": "NmlAtk5A1st",
			"Position": "Standing",
			"Input": "Standing_Any",
			"Button": 1,
			"Priority": 1,
			"CancelType": "Whenever",
			"CounterType": "Normal",
			"HitOrBlockCancels": [],
			"HitCancels": [],
			"WhiffCancels": [],
			"Looping": false,
			"LoopPos": 0,
			"NextState": "CmnStand",
			"LandToState": false,
			"LandState": "",
			"StateCanTurn": false,
			"TurnState": ""
		},
		{
			"Name": "NmlAtk5C",
			"Position": "Standing",
			"Input": "Standing_Any",
			"Button": 4,
			"Priority": 3,
			"CancelType": "Whenever",
			"CounterType": "Normal",
			"HitOrBlockCancels": [],
			"HitCancels": [],
			"WhiffCancels": [],
			"Looping": false,
			"LoopPos": 0,
			"NextState": "CmnStand",
			"LandToState": false,
			"LandState": "",
			"StateCanTurn": false,
			"TurnState": ""
		}
	],
	"SpecialStates": [],
	"SuperStates": []
}